<beans xmlns="http://xmlns.jcp.org/xml/ns/javaee"
	xmlns:xsi="http://www.w3.org/2001/XMLSchema-instance"
	xsi:schemaLocation="http://xmlns.jcp.org/xml/ns/javaee http://xmlns.jcp.org/xml/ns/javaee/beans_1_1.xsd"
	version="1.1" bean-discovery-mode="all">
	<scan>
		<exclude name="io.erenkaya.akaldiroglu._01_example.*" />
		<exclude name="io.erenkaya.akaldiroglu._02_example.*" />
		<exclude name="io.erenkaya.akaldiroglu._03_example.*" />
		<exclude name="io.erenkaya.akaldiroglu._04_example.*" />
		<exclude name="io.erenkaya.akaldiroglu._05_example.*" />
		<exclude name="io.erenkaya.akaldiroglu._06_example.*" />
		<exclude name="io.erenkaya.akaldiroglu._07_example.*" />
		<exclude name="io.erenkaya.akaldiroglu._07_example.*" />
		<exclude name="io.erenkaya.oacar.*" />
		<exclude name="io.erenkaya.spring._01_restservice.*" />
	</scan>
</beans>